stringutils/__init__.py
stringutils/caseconversion.py
stringutils-0.3.0.dist-info/DESCRIPTION.rst
stringutils-0.3.0.dist-info/METADATA
stringutils-0.3.0.dist-info/RECORD
stringutils-0.3.0.dist-info/WHEEL
stringutils-0.3.0.dist-info/metadata.json
stringutils-0.3.0.dist-info/top_level.txt
