Metadata-Version: 1.1
Name: stringutils
Version: 0.3.0
Summary: A functional string utility library for Python
Home-page: https://github.com/huntie/stringutils
Author: Alex Hunt
Author-email: hello@alexhunt.io
License: MIT
Keywords: string helpers transform
Platform: UNKNOWN
Classifier: Development Status :: 4 - Beta
Classifier: Intended Audience :: Developers
Classifier: License :: OSI Approved :: MIT License
Classifier: Topic :: Text Processing
Classifier: Topic :: Utilities
Classifier: Programming Language :: Python :: 2
Classifier: Programming Language :: Python :: 2.7
Classifier: Programming Language :: Python :: 3
Classifier: Programming Language :: Python :: 3.4
Classifier: Programming Language :: Python :: 3.5
Classifier: Programming Language :: Python :: 3.6
